argendolar/__init__.py
argendolar/argendolar.py
argendolar/tipo_dolares.py
model/__init__.py
argendolar-3.0.0.dist-info/LICENSE
argendolar-3.0.0.dist-info/METADATA
argendolar-3.0.0.dist-info/WHEEL
argendolar-3.0.0.dist-info/top_level.txt
argendolar-3.0.0.dist-info/RECORD
