Metadata-Version: 2.1
Name: argendolar
Version: 3.0.0
Summary: A package to get the exchange rates of the different types of dollars and others currencies in Argentina.
Home-page: https://github.com/Mgobeaalcoba/argendolar
Author: Mariano Gobea Alcoba
Author-email: gobeamariano@gmail.com
License: MIT
Classifier: Development Status :: 5 - Production/Stable
Classifier: Intended Audience :: Developers
Classifier: License :: OSI Approved :: MIT License
Classifier: Programming Language :: Python :: 3
Classifier: Programming Language :: Python :: 3.8
Requires-Python: >=3.8
License-File: LICENSE
Requires-Dist: pandas
Requires-Dist: requests
Requires-Dist: matplotlib
